typedtemplate/__init__.py
typedtemplate/engine.py
typedtemplate/template.py
typedtemplate/version.py
typedtemplate-0.2.1.dist-info/METADATA
typedtemplate-0.2.1.dist-info/WHEEL
typedtemplate-0.2.1.dist-info/licenses/LICENSE
typedtemplate-0.2.1.dist-info/RECORD
