Metadata-Version: 2.3
Name: typedtemplate
Version: 0.2.1
Summary: A typed string templating library using Pydantic
Author-email: Todd Cullen <todd@100-x.ai>
License: MIT
License-File: LICENSE
Requires-Python: >=3.9
Requires-Dist: pydantic>=2.6.3
Provides-Extra: jinja2
Requires-Dist: jinja2>=3.1.3; extra == 'jinja2'
